src/__init__.py
src/main.py
src/templates/.gitignore_template
src/templates/Dockerfile_template
src/templates/README_template.md
src/templates/confs_template/config.yaml
src/templates/confs_template/unit-test.yaml
src/templates/github_template/dependabot.yml
src/templates/github_template/workflows/ci.yml
src/templates/poetry/Dockerfile_template
src/templates/poetry/README_template.md
src/templates/poetry/poetry_template.toml
src/templates/poetry/pyproject_template.toml
src/templates/pyproject_template.toml
src/templates/pytest_template.ini
src/templates/requirements_template.txt
src/templates/src_template/__init__.py
src/templates/src_template/config.py
src/templates/src_template/constants.py
src/templates/src_template/database.py
src/templates/src_template/decos.py
src/templates/src_template/main.py
src/templates/src_template/routers/__init__.py
src/templates/src_template/routers/base.py
src/templates/src_template/routers/greeting/__init__.py
src/templates/src_template/routers/greeting/router.py
src/templates/src_template/routers/greeting/schema.py
src/templates/src_template/utils.py
src/templates/tests_template/__int__.py
src/templates/tests_template/conftest.py
src/templates/tests_template/test_greeting.py
src/version.py
create_fastapi_cli-0.1.1.dist-info/LICENSE
create_fastapi_cli-0.1.1.dist-info/METADATA
create_fastapi_cli-0.1.1.dist-info/WHEEL
create_fastapi_cli-0.1.1.dist-info/entry_points.txt
create_fastapi_cli-0.1.1.dist-info/RECORD
