Metadata-Version: 2.1
Name: create-fastapi-cli
Version: 0.1.1
Summary: A cli for creating fastapi project quickly.
Author: yugangcao
Author-email: yugang.cao12@gmail.com
Requires-Python: >=3.10,<4.0
Classifier: Programming Language :: Python :: 3
Classifier: Programming Language :: Python :: 3.10
Classifier: Programming Language :: Python :: 3.11
Classifier: Programming Language :: Python :: 3.12
Classifier: Programming Language :: Python :: 3.13
Requires-Dist: importlib-resources (>=6.4.5,<7.0.0)
Requires-Dist: jinja2 (>=3.1.4,<4.0.0)
